pywrap.py
pywrap-0.1.0.dist-info/DESCRIPTION.rst
pywrap-0.1.0.dist-info/METADATA
pywrap-0.1.0.dist-info/metadata.json
pywrap-0.1.0.dist-info/RECORD
pywrap-0.1.0.dist-info/top_level.txt
pywrap-0.1.0.dist-info/WHEEL
