Metadata-Version: 2.0
Name: pywrap
Version: 0.1.0
Summary: Ctypes made easy.
Home-page: https://github.com/tmr232/pywrap
Author: Tamir Bahar
Author-email: UNKNOWN
License: MIT
Platform: UNKNOWN
